simul/__init__.py
simul/over.py
simul/py.typed
simul/analyze/__init__.py
simul/executor/__init__.py
simul/executor/executor.py
simul/executor/serial_executor.py
simul/executor/thread_pool_executor.py
simul/function/__init__.py
simul/function/parallel_function.py
simul/function/validate.py
simul/function/visitor.py
simul-0.1.0.dist-info/METADATA
simul-0.1.0.dist-info/WHEEL
simul-0.1.0.dist-info/licenses/LICENSE
simul-0.1.0.dist-info/RECORD
